ez1/__init__.py
tests/__init__.py
tests/conftest.py
tests/helpers/__init__.py
tests/helpers/config.py
tests/integration/__init__.py
tests/integration/test_download_flow.py
tests/integration/test_file_operations.py
tests/integration/test_upload_flow.py
tests/unit/__init__.py
tests/unit/test_api_calls.py
tests/unit/test_client_init.py
tests/unit/test_encryption.py
tests/unit/test_error_handling.py
ez1_python_sdk-1.0.1.dist-info/METADATA
ez1_python_sdk-1.0.1.dist-info/WHEEL
ez1_python_sdk-1.0.1.dist-info/top_level.txt
ez1_python_sdk-1.0.1.dist-info/RECORD
