Metadata-Version: 2.4
Name: ez1-python-sdk
Version: 1.0.1
Summary: Official Python SDK for EasyOne API with client-side encryption
Home-page: https://github.com/ez1-cc/python-sdk
Author: ez1
Project-URL: Bug Reports, https://github.com/ez1-cc/python-sdk/issues
Project-URL: Source, https://github.com/ez1-cc/python-sdk
Keywords: ez1 file-upload encryption aes-gcm storage sdk
Classifier: Development Status :: 4 - Beta
Classifier: Intended Audience :: Developers
Classifier: Topic :: Software Development :: Libraries :: Python Modules
Classifier: License :: OSI Approved :: MIT License
Classifier: Programming Language :: Python :: 3
Classifier: Programming Language :: Python :: 3.8
Classifier: Programming Language :: Python :: 3.9
Classifier: Programming Language :: Python :: 3.10
Classifier: Programming Language :: Python :: 3.11
Classifier: Programming Language :: Python :: 3.12
Requires-Python: >=3.8
Requires-Dist: requests>=2.31.0
Requires-Dist: cryptography>=41.0.0
Provides-Extra: dev
Requires-Dist: pytest>=7.4.0; extra == "dev"
Requires-Dist: pytest-cov>=4.1.0; extra == "dev"
Requires-Dist: black>=23.0.0; extra == "dev"
Requires-Dist: mypy>=1.5.0; extra == "dev"
Dynamic: author
Dynamic: classifier
Dynamic: description
Dynamic: description-content-type
Dynamic: home-page
Dynamic: keywords
Dynamic: project-url
Dynamic: provides-extra
Dynamic: requires-dist
Dynamic: requires-python
Dynamic: summary
